urlquote-2.2.0.dist-info/METADATA
urlquote-2.2.0.dist-info/WHEEL
urlquote-2.2.0.dist-info/licenses/LICENSE
urlquote/__init__.py
urlquote/quoting.py
urlquote/urlquote/__init__.py
urlquote/urlquote/ffi.py
urlquote/urlquote/liburlquote.dylib
urlquote-2.2.0.dist-info/RECORD
