Metadata-Version: 2.4
Name: urlquote
Version: 2.2.0
Requires-Dist: cffi
Requires-Dist: pytest<8.0.0 ; extra == 'test'
Provides-Extra: test
License-File: LICENSE
Summary: Fast quoting and unquoting of urls.
Author-email: Blue Yonder <oss@blue-yonder.com>
Project-URL: repository, https://github.com/blue-yonder/urlquote
Project-URL: changelog, https://github.com/blue-yonder/urlquote/main/Changelog.md
